schemdraw/__init__.py
schemdraw/default_canvas.py
schemdraw/drawing_stack.py
schemdraw/py.typed
schemdraw/schemdraw.py
schemdraw/segments.py
schemdraw/style.py
schemdraw/transform.py
schemdraw/types.py
schemdraw/util.py
schemdraw/backends/__init__.py
schemdraw/backends/matrix.py
schemdraw/backends/mpl.py
schemdraw/backends/svg.py
schemdraw/backends/svgtext.py
schemdraw/backends/svgunits.py
schemdraw/dsp/__init__.py
schemdraw/dsp/dsp.py
schemdraw/elements/__init__.py
schemdraw/elements/cables.py
schemdraw/elements/compound.py
schemdraw/elements/connectors.py
schemdraw/elements/container.py
schemdraw/elements/elements.py
schemdraw/elements/image.py
schemdraw/elements/intcircuits.py
schemdraw/elements/lines.py
schemdraw/elements/misc.py
schemdraw/elements/oneterm.py
schemdraw/elements/opamp.py
schemdraw/elements/outlets.py
schemdraw/elements/sources.py
schemdraw/elements/switches.py
schemdraw/elements/transistors.py
schemdraw/elements/twoports.py
schemdraw/elements/twoterm.py
schemdraw/elements/xform.py
schemdraw/flow/__init__.py
schemdraw/flow/flow.py
schemdraw/logic/__init__.py
schemdraw/logic/kmap.py
schemdraw/logic/logic.py
schemdraw/logic/table.py
schemdraw/logic/timing.py
schemdraw/logic/timingwaves.py
schemdraw/parsing/__init__.py
schemdraw/parsing/buchheim.py
schemdraw/parsing/logic_parser.py
schemdraw/pictorial/__init__.py
schemdraw/pictorial/fritz.py
schemdraw/pictorial/pictorial.py
schemdraw-0.21.dist-info/licenses/LICENSE.txt
schemdraw-0.21.dist-info/METADATA
schemdraw-0.21.dist-info/WHEEL
schemdraw-0.21.dist-info/top_level.txt
schemdraw-0.21.dist-info/RECORD
