Metadata-Version: 2.4
Name: schemdraw
Version: 0.21
Summary: Electrical circuit schematic drawing
Home-page: https://schemdraw.readthedocs.io
Author: Collin J. Delker
Author-email: code@collindelker.com
License: MIT
Project-URL: Documentation, https://schemdraw.readthedocs.io
Project-URL: Source Code, https://github.com/cdelker/schemdraw
Keywords: circuit,schematic,electrical,flowchart,logic
Classifier: Development Status :: 4 - Beta
Classifier: Programming Language :: Python :: 3
Classifier: Programming Language :: Python :: 3.9
Classifier: Programming Language :: Python :: 3.10
Classifier: Programming Language :: Python :: 3.11
Classifier: Programming Language :: Python :: 3.12
Classifier: Programming Language :: Python :: 3.13
Classifier: Operating System :: OS Independent
Classifier: Intended Audience :: Education
Classifier: Intended Audience :: Science/Research
Classifier: Intended Audience :: End Users/Desktop
Requires-Python: >=3.9
License-File: LICENSE.txt
Provides-Extra: matplotlib
Requires-Dist: matplotlib>=3.4; extra == "matplotlib"
Provides-Extra: svgmath
Requires-Dist: ziafont>=0.10; extra == "svgmath"
Requires-Dist: ziamath>=0.12; extra == "svgmath"
Requires-Dist: latex2mathml; extra == "svgmath"
Dynamic: license-file
